LICENSE
MANIFEST.in
README.md
setup.py
demographica/__init__.py
demographica/demographica.py
demographica/utils.py
demographica.egg-info/PKG-INFO
demographica.egg-info/SOURCES.txt
demographica.egg-info/dependency_links.txt
demographica.egg-info/requires.txt
demographica.egg-info/top_level.txt
demographica/../LICENSE
demographica/../README.md
demographica/datasets/NameDistributions.csv
demographica/datasets/SexDistributions.csv
demographica/datasets/US Age Dist.csv
demographica/datasets/age_distribution.csv
demographica/datasets/counts_by_age_sex_name.csv
demographica/datasets/sample_first_names.tsv