Metadata-Version: 1.1
Name: demographica
Version: 0.2.4.1
Summary: A Python Package to infer ages using US Census Data
Home-page: https://github.com/CamDavidsonPilon/demographica
Author: Cameron Davidson-Pilon
Author-email: cam.davidson.pilon@gmail.com
License: MIT
Platform: UNKNOWN
Classifier: Development Status :: 4 - Beta
Classifier: License :: OSI Approved :: MIT License
Classifier: Programming Language :: Python
Classifier: Topic :: Scientific/Engineering
